ponder/__init__.py
ponder/_version.py
ponder/command_line.py
ponder/common.py
ponder/instrumentation.py
ponder/core/__init__.py
ponder/core/abstract_connection.py
ponder/core/abstract_dialect.py
ponder/core/apply.py
ponder/core/common.py
ponder/core/connection_dialect_mixin.py
ponder/core/dataframe.py
ponder/core/dataframequerytreehelper.py
ponder/core/debug_vis.py
ponder/core/error_codes.py
ponder/core/index.py
ponder/core/io.py
ponder/core/pivot.py
ponder/core/query_compiler.py
ponder/core/query_tree.py
ponder/core/registry.py
ponder/core/sql_connection.py
ponder/core/sql_dialect.py
ponder/engines/__init__.py
ponder/engines/bigquery/__init__.py
ponder/engines/bigquery/bigquery_dialect.py
ponder/engines/bigquery/connection.py
ponder/engines/bigquery/io.py
ponder/engines/duckdb/__init__.py
ponder/engines/duckdb/connection.py
ponder/engines/duckdb/duckdb_dialect.py
ponder/engines/duckdb/io.py
ponder/engines/mssql/__init__.py
ponder/engines/mssql/connection.py
ponder/engines/mssql/io.py
ponder/engines/mssql/mssql_dialect.py
ponder/engines/postgres/__init__.py
ponder/engines/postgres/connection.py
ponder/engines/postgres/io.py
ponder/engines/postgres/postgres_dialect.py
ponder/engines/redshift/__init__.py
ponder/engines/redshift/connection.py
ponder/engines/redshift/io.py
ponder/engines/redshift/redshift_dialect.py
ponder/engines/snowflake/__init__.py
ponder/engines/snowflake/connection.py
ponder/engines/snowflake/io.py
ponder/engines/snowflake/snowflake_dialect.py
ponder-0.2.6.dist-info/LICENSE.txt
ponder-0.2.6.dist-info/METADATA
ponder-0.2.6.dist-info/WHEEL
ponder-0.2.6.dist-info/entry_points.txt
ponder-0.2.6.dist-info/top_level.txt
ponder-0.2.6.dist-info/RECORD
